fredipy/__init__.py
fredipy/constraints.py
fredipy/covariance.py
fredipy/integrators.py
fredipy/kernels.py
fredipy/models.py
fredipy/operators.py
fredipy/util.py
fredipy-0.2.0.dist-info/licenses/LICENSE
fredipy-0.2.0.dist-info/METADATA
fredipy-0.2.0.dist-info/WHEEL
fredipy-0.2.0.dist-info/top_level.txt
fredipy-0.2.0.dist-info/RECORD
