Metadata-Version: 2.4
Name: fredipy
Version: 0.2.0
Summary: Inverting Fredholm Integrals with Python
Author-email: Jonas Turnwald <jonas.turnwald@tu-darmstadt.de>, "Julian M. Urban" <jurban@mit.edu>, Nicolas Wink <tbd@tbd.com>
License: MIT License
Project-URL: Repository, https://github.com/JonasTurnwald/fredipy
Keywords: gaussian-process,fredholm,inverse-problem
Classifier: Development Status :: 3 - Alpha
Classifier: Intended Audience :: Science/Research
Classifier: License :: OSI Approved :: MIT License
Classifier: Programming Language :: Python :: 3.11
Classifier: Programming Language :: Python :: 3.10
Classifier: Topic :: Scientific/Engineering :: Mathematics
Classifier: Topic :: Scientific/Engineering :: Physics
Requires-Python: >=3.10
License-File: LICENSE
Requires-Dist: numpy
Requires-Dist: scipy
Provides-Extra: test
Requires-Dist: pytest; extra == "test"
Provides-Extra: examples
Requires-Dist: matplotlib; extra == "examples"
Dynamic: license-file
